setup.cfg
setup.py
PyLogo.egg-info/PKG-INFO
PyLogo.egg-info/SOURCES.txt
PyLogo.egg-info/dependency_links.txt
PyLogo.egg-info/entry_points.txt
PyLogo.egg-info/top_level.txt
docs/LogoLanguage.txt
docs/PyLogo.txt
docs/TODO.txt
docs/UCBManual.txt
docs/api.txt
docs/build
docs/index.txt
docs/license.txt
docs/test_oo.txt
docs/tests.txt
examples/bench.logo
examples/bench.ucblogo
examples/bench2.ucblogo
examples/chaser.logo
examples/factorial.logo
examples/population.logo
examples/racer.logo
examples/spawn.logo
examples/square_root.logo
examples/squares.logo
examples/test.logo
examples/notused/pascal.logo
examples/notused/regression-environment.logo
examples/notused/regression.logo
examples/notused/turing.logo
pylogo/__init__.py
pylogo/builtins.py
pylogo/common.py
pylogo/ide.py
pylogo/init.logo
pylogo/interpreter.py
pylogo/logo_turtle.py
pylogo/logodoctest.py
pylogo/objectintrospect.py
pylogo/oobuiltins.py
pylogo/reader.py
pylogo/script.py
pylogo/ucbcompat.py
pylogo/wxide.py
pylogo/defs/defs.html
pylogo/defs/defs.txt
pylogo/defs/turtle.logodef
