Metadata-Version: 1.0
Name: PyLogo
Version: 0.3
Summary: Logo interpreter
Home-page: http://pylogo.org
Author: Ian Bicking
Author-email: ianb@colorstudy.com
License: MIT
Platform: UNKNOWN
Classifier: Development Status :: 3 - Beta
Classifier: Intended Audience :: Education
Classifier: License :: OSI Approved :: MIT License
Classifier: Programming Language :: Logo
Classifier: Programming Language :: Python
Classifier: Topic :: Education
Classifier: Topic :: Software Development :: Interpreters
